odoo/addons/web_widget_dropdown_dynamic_example/README.rst
odoo/addons/web_widget_dropdown_dynamic_example/__init__.py
odoo/addons/web_widget_dropdown_dynamic_example/__manifest__.py
odoo/addons/web_widget_dropdown_dynamic_example/i18n/ca.po
odoo/addons/web_widget_dropdown_dynamic_example/i18n/es.po
odoo/addons/web_widget_dropdown_dynamic_example/i18n/fr.po
odoo/addons/web_widget_dropdown_dynamic_example/i18n/pt_BR.po
odoo/addons/web_widget_dropdown_dynamic_example/i18n/web_widget_dropdown_dynamic_example.pot
odoo/addons/web_widget_dropdown_dynamic_example/models/__init__.py
odoo/addons/web_widget_dropdown_dynamic_example/models/web_widget_dropdown_dynamic_example.py
odoo/addons/web_widget_dropdown_dynamic_example/readme/DESCRIPTION.rst
odoo/addons/web_widget_dropdown_dynamic_example/static/description/icon.png
odoo/addons/web_widget_dropdown_dynamic_example/static/description/index.html
odoo/addons/web_widget_dropdown_dynamic_example/views/web_widget_dropdown_dynamic_example.xml
odoo12_addon_web_widget_dropdown_dynamic_example-12.0.1.0.1.dist-info/METADATA
odoo12_addon_web_widget_dropdown_dynamic_example-12.0.1.0.1.dist-info/WHEEL
odoo12_addon_web_widget_dropdown_dynamic_example-12.0.1.0.1.dist-info/top_level.txt
odoo12_addon_web_widget_dropdown_dynamic_example-12.0.1.0.1.dist-info/RECORD
